setup.py
TweetPony.egg-info/PKG-INFO
TweetPony.egg-info/SOURCES.txt
TweetPony.egg-info/dependency_links.txt
TweetPony.egg-info/requires.txt
TweetPony.egg-info/top_level.txt
tweetpony/__init__.py
tweetpony/api.py
tweetpony/endpoints.py
tweetpony/error.py
tweetpony/metadata.py
tweetpony/models.py
tweetpony/utils.py