Metadata-Version: 1.0
Name: TweetPony
Version: 1.2.7
Summary: A Twitter library for Python
Home-page: https://github.com/Mezgrman/TweetPony
Author: Julian Metzler
Author-email: contact@mezgrman.de
License: AGPLv3
Keywords: twitter library api wrapper pony
Platform: UNKNOWN
